{
  "project_info": {
    "project_number": "901407876353",
    "project_id": "kraftopia-46aaa",
    "storage_bucket": "kraftopia-46aaa.appspot.com"
  },
  "client": [
    {
      "client_info": {
        "mobilesdk_app_id": "1:901407876353:android:97d80a0db0e99b363c6700",
        "android_client_info": {
          "package_name": "com.example.kraftopia"
        }
      },
      "oauth_client": [
        {
          "client_id": "901407876353-llqcabkdotrimk558qibdc2vkj96r5v1.apps.googleusercontent.com",
          "client_type": 3
        }
      ],
      "api_key": [
        {
          "current_key": "AIzaSyAO1RcrKVEclXPZR95rM0r7AEKPean3oso"
        }
      ],
      "services": {
        "appinvite_service": {
          "other_platform_oauth_client": [
            {
              "client_id": "901407876353-llqcabkdotrimk558qibdc2vkj96r5v1.apps.googleusercontent.com",
              "client_type": 3
            }
          ]
        }
      }
    }
  ],
  "configuration_version": "1"
}